setup.cfg
setup.py
Python_Trivia_API.egg-info/PKG-INFO
Python_Trivia_API.egg-info/SOURCES.txt
Python_Trivia_API.egg-info/dependency_links.txt
Python_Trivia_API.egg-info/requires.txt
Python_Trivia_API.egg-info/top_level.txt
pytrivia/__helpers.py
pytrivia/__init__.py
pytrivia/enums.py
pytrivia/trivia.py